NotionPinecone/__init__.py
NotionPinecone/embedding.py
NotionPinecone/notion.py
NotionPinecone/pinecone.py
NotionPinecone/utils.py
notion_pinecone-0.0.24.dist-info/LICENSE
notion_pinecone-0.0.24.dist-info/METADATA
notion_pinecone-0.0.24.dist-info/WHEEL
notion_pinecone-0.0.24.dist-info/top_level.txt
notion_pinecone-0.0.24.dist-info/RECORD
